package_xskj_NetworkXsimple/__init__.py
package_xskj_NetworkXsimple/__version__.py
package_xskj_NetworkXsimple/core.py
NetworkXsimple-0.2.1.dist-info/LICENSE
NetworkXsimple-0.2.1.dist-info/METADATA
NetworkXsimple-0.2.1.dist-info/WHEEL
NetworkXsimple-0.2.1.dist-info/top_level.txt
NetworkXsimple-0.2.1.dist-info/RECORD
