Metadata-Version: 2.1
Name: NetworkXsimple
Version: 0.2.1
Summary: This is a simple encapsulation for networkX, which further simplifies the process of networkX for drawing neural network diagrams, so that the author can only focus on the logical writing of neural networks, without spending time on the visual presentation of neural networks. At the same time, this module also inherits all the methods of network and does not affect the normal function calls of networkX.
Home-page: https://github.com/gnu-xiaosong/networkXsimple.git
Author: xskj
Author-email: 1829134124@qq.com
License: MIT
Platform: UNKNOWN
Classifier: License :: OSI Approved :: MIT License
Classifier: Programming Language :: Python
Classifier: Programming Language :: Python :: 3
Classifier: Programming Language :: Python :: 3.6
Classifier: Programming Language :: Python :: Implementation :: CPython
Classifier: Programming Language :: Python :: Implementation :: PyPy
Requires-Python: >=3.6.0
